{
 "data_point" :  {
  "analysis_uuid" : "a8feca85-dab9-4510-8610-651ef847781d",
  "complete" : false,
  "data_point_type" : "DataPoint",
  "display_name" : "Reduce Lighting Load By 50 percent Only",
  "failed" : false,
  "name" : "Reduce Lighting Load By 50 percent Only",
  "problem_uuid" : "412b1879-f0ee-4919-ab90-6ab642fd39ee",
  "uuid" : "6fdfb005-11fa-4667-bb6c-411c120b123e",
  "variable_values" : [
   {
    "value" : 0,
    "value_type" : "int",
    "variable_value_index" : 0
   },
   {
    "value" : 0,
    "value_type" : "int",
    "variable_value_index" : 1
   },
   {
    "value" : 2,
    "value_type" : "int",
    "variable_value_index" : 2
   },
   {
    "value" : 0,
    "value_type" : "int",
    "variable_value_index" : 3
   }
  ],
  "version_uuid" : "6da4a714-f6bf-4f08-a072-f143c1cd4c7f"
 },
 "metadata" :  {
  "openstudio_version" : "1.0.3"
 }
}